MANIFEST.in
README.md
setup.py
data/kema.ini
data/templates/header.tmpl.h
data/templates/source.tmpl.c
kema/__init__.py
kema/app.py
kema.egg-info/PKG-INFO
kema.egg-info/SOURCES.txt
kema.egg-info/dependency_links.txt
kema.egg-info/entry_points.txt
kema.egg-info/requires.txt
kema.egg-info/top_level.txt