Metadata-Version: 1.0
Name: kema
Version: 0.3.0
Summary: A small package to help setting up projects
Home-page: https://github.com/nelsonmestevao/kema
Author: Nelson Estevão
Author-email: hello@estevao.xyz
License: UNKNOWN
Platform: UNKNOWN
